[
    {
        "totalcount": 1,
        "cmt_c": 1,
        "Voting_Activity_Ids": {
            "Agreed": [],
            "Disagreed": []
        }
    },
    {
        "_id": 2687661751,
        "A": "B",
        "B": "B",
        "SPAM_VAL": {
            "model_num": "/opt/spam_ml/spam_ml_frozen_models/model_keras_100L_13L_20201105-200252/spam_classifier_0.030348",
            "isSpam": false,
            "round_prob": "0.00001",
            "lan": "eng"
        },
        "A_ID": 782151188,
        "C_D": "15 minutes ago",
        "type": "ARTICLE",
        "A_K": "TOI",
        "A_N": "Commented",
        "A_D_N": "Abc",
        "U": "U",
        "A_D_N_U": null,
        "C_T": "good to have renewable energy and atomic energy to meet future demands.",
        "IS_C_M_M": "true",
        "A_U_I": "2687661751",
        "m_r": null,
        "tet": "PM Modi in Banswara: Nuclear power plant among Rs 1.22 lakh cr worth of projects unveiled; green energy in focus",
        "GID": 52026830920,
        "ad": null,
        "teu": "https://timesofindia.indiatimes.com/toi-plus/international/was-trumps-speech-the-most-misleading-youll-ever-hear-at-the-un-general-assembly/articleshow/124084329.cms",
        "tesyn": "Prime Minister Modi initiated projects worth over Rs 1.22 lakh crore in Rajasthan, including the Rs 42,000 crore Mahi Banswara Atomic Power Project, featuring four 700 MW reactors. He also launched renewable energy projects valued at nearly Rs 19,210 crore. Earlier, he inaugurated the Uttar Pradesh International Trade Show 2025 in Greater Noida.",
        "B_ID": 45279934,
        "U_R": "",
        "iu": "https://timesofindia.indiatimes.com/icons/toifavicon.ico",
        "AC_D_C": 0,
        "O_ID": 45279934,
        "AC_A_C": 0,
        "AC_O_C": 0,
        "msid": "124114870",
        "C_R_EROID": null,
        "IS_C_M": "true",
        "CITY": "",
        "ERO_D": "{\"roaltdetails\":{\"rootid\":0,\"pcode\":\"TOI\",\"medium\":\"WEB\",\"rotype\":0,\"userName\":\"Abc\",\"graph\":1,\"fromname\":\"Abc\",\"url\":\"https://timesofindia.indiatimes.com/toi-plus/international/was-trumps-speech-the-most-misleading-youll-ever-hear-at-the-un-general-assembly/articleshow/124084329.cms\",\"parentid\":0,\"loggedstatus\":1,\"configid\":41083278,\"imageurl\":\"https://jssocdn.indiatimes.com/image/default.png\",\"urs\":\"\",\"location\":\"\",\"roType\":0}}",
        "F_NAME": "Abc ",
        "C_RO_T": "0",
        "PIU": "",
        "AC_R_C": 0,
        "C_D_Minute": 29313351,
        "A_DT": "1758801073117",
        "user_detail": {
            "_id": 782151188,
            "uid": "anluuv2cy232urmjc0gaacpy8",
            "F_N": "Abc",
            "L_N": null,
            "F_C": 2,
            "FE_C": 1,
            "thumb": "",
            "I_U_A": "false",
            "original": "",
            "profile": "",
            "CITY": "",
            "FL_N": "Abc",
            "tiny": ""
        },
        "user_reward_point_info": null
    }
]